[
  {
    "id": "458702",
    "date": "2025-05-12 06:04:59+00:00",
    "text": "💊 $linging (yo phone linging) \nFFXHGDCUWiq5t7tevwzYx3wtMm9B1a33tQgg3AsYpump\n\n💰 Marketcap: $96.13K\n\n🟢 CALLS - 15\n\n12 MAY (UTC)\n1. 4AM Pumpfun Volume Signal \n└ 05:28:37\n2. THE DEGEN BOYS \n└ 05:29:23\n3. Savannah Wakanda ℗ \n└ 05:29:27\n4. Moo Deng President \n└ 05:40:39\n5. Apex Solana Signal \n└ 05:59:33\n6. Kingdom of Degen CALLS \n└ 05:59:37\n7. 🚨 SHITCOIN GEMS ALERT 🚨 \n└ 05:59:43\n8. 4AM Solana Volume Signal \n└ 05:59:46\n9. OpalGems | Channel \n└ 05:59:53\n10. SolHouse Signal \n└ 05:59:59\n11. Ranma Calls - Solana \n└ 06:00:26\n12. Pump.fun Premium Call 💊 \n└ 06:00:33\n13. Crypto Mafia Plays \n└ 06:00:47\n14. Memes Don’t Lies \n└ 06:04:15\n15. ZODIGEM - BOT SIGNAL 🆕\n└ 06:04:56\n\nAfter 44 sec of open trading, the first community call was initiated (promoted very early)\n\n🟢 Website \n\nDextools | Dexscreener | Pump",
    "links": [
      "https://t.me/SAVANNAHCALLS/40596",
      "https://t.me/ApexSolanaSignal/11558",
      "https://t.me/OpalGemsCall/3554",
      "https://t.me/solhousesignal/50845",
      "https://www.pump.fun/FFXHGDCUWiq5t7tevwzYx3wtMm9B1a33tQgg3AsYpump",
      "https://t.me/MemesDontLies/96054",
      "https://t.me/ZodiGemAlpha/7920",
      "https://t.me/signalsolanaby4am/74202",
      "https://t.me/TheDegenBoysLounge/27875",
      "https://t.me/shitcoingemsalert/61808",
      "https://t.me/Ranma_Calls_Solana/17131",
      "https://solscan.io/token/FFXHGDCUWiq5t7tevwzYx3wtMm9B1a33tQgg3AsYpump",
      "https://www.dextools.io/app/en/solana/pair-explorer/FFXHGDCUWiq5t7tevwzYx3wtMm9B1a33tQgg3AsYpump",
      "https://t.me/pumpfunvolumeby4AM/58676",
      "https://t.me/CryptoMafiaPlays/12766",
      "https://dexscreener.com/solana/FFXHGDCUWiq5t7tevwzYx3wtMm9B1a33tQgg3AsYpump",
      "https://t.me/KingdomOfDegenCalls/51305",
      "https://t.me/Pumpfunpremium/19530",
      "https://t.me/MooDengPresidentCallers/59412",
      "https://www.tiktok.com/%40captainelliebro/video/7468558903731555614?q=linging&t=1747026239235"
    ]
  },
  {
    "id": "458703",
    "date": "2025-05-12 06:05:05+00:00",
    "text": "💊 $HIKARI (HIKARI) \n5VwtHytVq532hEnyWDMy6mNdgpNFAAhk2wTUogY6pump\n\n💰 Marketcap: $101.81K\n\n🟢 CALLS - 5\n\n12 MAY (UTC)\n1. 4AM Pumpfun Volume Signal \n└ 05:25:49\n2. Savannah Wakanda ℗ \n└ 05:25:58\n3. THE DEGEN BOYS \n└ 05:26:14\n4. 🚨 SHITCOIN GEMS ALERT 🚨 \n└ 06:04:41\n5. Kingdom of Degen CALLS 🆕\n└ 06:05:02\n\nAfter 2 min 59 sec of open trading, the first community call was initiated (promoted very early)\n\n🟢 Telegram | Twitter | Website \n\nDextools | Dexscreener | Pump\n\n👉 Experience Dogee on BSC for Lightning-Fast Copy Trading",
    "links": [
      "https://t.me/SAVANNAHCALLS/40595",
      "https://t.me/KingdomOfDegenCalls/51308",
      "https://dexscreener.com/solana/5VwtHytVq532hEnyWDMy6mNdgpNFAAhk2wTUogY6pump",
      "https://t.me/TheDegenBoysLounge/27873",
      "https://x.com/itshikari_fun",
      "https://www.dextools.io/app/en/solana/pair-explorer/5VwtHytVq532hEnyWDMy6mNdgpNFAAhk2wTUogY6pump",
      "https://t.me/pumpfunvolumeby4AM/58674",
      "https://www.pump.fun/5VwtHytVq532hEnyWDMy6mNdgpNFAAhk2wTUogY6pump",
      "https://t.me/shitcoingemsalert/61810",
      "https://itshikari.xyz/",
      "https://t.me/itshikari_fun",
      "https://solscan.io/token/5VwtHytVq532hEnyWDMy6mNdgpNFAAhk2wTUogY6pump",
      "https://t.me/dogeebsc_bot?start=inv-1524500950"
    ]
  },
  {
    "id": "458704",
    "date": "2025-05-12 06:05:16+00:00",
    "text": "💊 $HIKARI (HIKARI) \n5VwtHytVq532hEnyWDMy6mNdgpNFAAhk2wTUogY6pump\n\n💰 Marketcap: $105.05K\n\n🟢 CALLS - 6\n\n12 MAY (UTC)\n1. 4AM Pumpfun Volume Signal \n└ 05:25:49\n2. Savannah Wakanda ℗ \n└ 05:25:58\n3. THE DEGEN BOYS \n└ 05:26:14\n4. 🚨 SHITCOIN GEMS ALERT 🚨 \n└ 06:04:41\n5. Kingdom of Degen CALLS \n└ 06:05:02\n6. Ranma Calls - Solana 🆕\n└ 06:05:14\n\nAfter 2 min 59 sec of open trading, the first community call was initiated (promoted very early)\n\n🟢 Telegram | Twitter | Website \n\nDextools | Dexscreener | Pump",
    "links": [
      "https://t.me/SAVANNAHCALLS/40595",
      "https://t.me/KingdomOfDegenCalls/51308",
      "https://dexscreener.com/solana/5VwtHytVq532hEnyWDMy6mNdgpNFAAhk2wTUogY6pump",
      "https://t.me/TheDegenBoysLounge/27873",
      "https://x.com/itshikari_fun",
      "https://www.dextools.io/app/en/solana/pair-explorer/5VwtHytVq532hEnyWDMy6mNdgpNFAAhk2wTUogY6pump",
      "https://t.me/pumpfunvolumeby4AM/58674",
      "https://www.pump.fun/5VwtHytVq532hEnyWDMy6mNdgpNFAAhk2wTUogY6pump",
      "https://t.me/shitcoingemsalert/61810",
      "https://itshikari.xyz/",
      "https://t.me/itshikari_fun",
      "https://solscan.io/token/5VwtHytVq532hEnyWDMy6mNdgpNFAAhk2wTUogY6pump",
      "https://t.me/Ranma_Calls_Solana/17134"
    ]
  },
  {
    "id": "458705",
    "date": "2025-05-12 06:05:31+00:00",
    "text": "💊 $HIKARI (HIKARI) \n5VwtHytVq532hEnyWDMy6mNdgpNFAAhk2wTUogY6pump\n\n💰 Marketcap: $104.37K\n\n🟢 CALLS - 7\n\n12 MAY (UTC)\n1. 4AM Pumpfun Volume Signal \n└ 05:25:49\n2. Savannah Wakanda ℗ \n└ 05:25:58\n3. THE DEGEN BOYS \n└ 05:26:14\n4. 🚨 SHITCOIN GEMS ALERT 🚨 \n└ 06:04:41\n5. Kingdom of Degen CALLS \n└ 06:05:02\n6. Ranma Calls - Solana \n└ 06:05:14\n7. Pump.fun Premium Call 💊 🆕\n└ 06:05:28\n\nAfter 2 min 59 sec of open trading, the first community call was initiated (promoted very early)\n\n🟢 Telegram | Twitter | Website \n\nDextools | Dexscreener | Pump",
    "links": [
      "https://t.me/SAVANNAHCALLS/40595",
      "https://t.me/KingdomOfDegenCalls/51308",
      "https://dexscreener.com/solana/5VwtHytVq532hEnyWDMy6mNdgpNFAAhk2wTUogY6pump",
      "https://t.me/Pumpfunpremium/19531",
      "https://t.me/TheDegenBoysLounge/27873",
      "https://x.com/itshikari_fun",
      "https://www.dextools.io/app/en/solana/pair-explorer/5VwtHytVq532hEnyWDMy6mNdgpNFAAhk2wTUogY6pump",
      "https://t.me/pumpfunvolumeby4AM/58674",
      "https://www.pump.fun/5VwtHytVq532hEnyWDMy6mNdgpNFAAhk2wTUogY6pump",
      "https://t.me/shitcoingemsalert/61810",
      "https://itshikari.xyz/",
      "https://t.me/itshikari_fun",
      "https://solscan.io/token/5VwtHytVq532hEnyWDMy6mNdgpNFAAhk2wTUogY6pump",
      "https://t.me/Ranma_Calls_Solana/17134"
    ]
  },
  {
    "id": "458706",
    "date": "2025-05-12 06:05:43+00:00",
    "text": "💊 $HIKARI (HIKARI) \n5VwtHytVq532hEnyWDMy6mNdgpNFAAhk2wTUogY6pump\n\n💰 Marketcap: $108.24K\n\n🟢 CALLS - 8\n\n12 MAY (UTC)\n1. 4AM Pumpfun Volume Signal \n└ 05:25:49\n2. Savannah Wakanda ℗ \n└ 05:25:58\n3. THE DEGEN BOYS \n└ 05:26:14\n4. 🚨 SHITCOIN GEMS ALERT 🚨 \n└ 06:04:41\n5. Kingdom of Degen CALLS \n└ 06:05:02\n6. Ranma Calls - Solana \n└ 06:05:14\n7. Pump.fun Premium Call 💊 \n└ 06:05:28\n8. OpalGems | Channel 🆕\n└ 06:05:40\n\nAfter 2 min 59 sec of open trading, the first community call was initiated (promoted very early)\n\n🟢 Telegram | Twitter | Website \n\nDextools | Dexscreener | Pump",
    "links": [
      "https://t.me/SAVANNAHCALLS/40595",
      "https://t.me/KingdomOfDegenCalls/51308",
      "https://dexscreener.com/solana/5VwtHytVq532hEnyWDMy6mNdgpNFAAhk2wTUogY6pump",
      "https://t.me/Pumpfunpremium/19531",
      "https://t.me/TheDegenBoysLounge/27873",
      "https://t.me/OpalGemsCall/3555",
      "https://x.com/itshikari_fun",
      "https://www.dextools.io/app/en/solana/pair-explorer/5VwtHytVq532hEnyWDMy6mNdgpNFAAhk2wTUogY6pump",
      "https://t.me/pumpfunvolumeby4AM/58674",
      "https://www.pump.fun/5VwtHytVq532hEnyWDMy6mNdgpNFAAhk2wTUogY6pump",
      "https://t.me/shitcoingemsalert/61810",
      "https://itshikari.xyz/",
      "https://t.me/itshikari_fun",
      "https://solscan.io/token/5VwtHytVq532hEnyWDMy6mNdgpNFAAhk2wTUogY6pump",
      "https://t.me/Ranma_Calls_Solana/17134"
    ]
  }
]