[
  {
    "id": "465619",
    "date": "2025-05-14 21:38:34+00:00",
    "text": "$ABC (Always Be Coding) \n7CCeK4AZJQUxipj7vqGRo8d6pg6NDGiP1XMCdALFV5Bj\n\n💰 Marketcap: $364.86K\n\nCALLS - 1\n\n14 MAY (UTC)\n1. Apex Solana Signal 🆕\n└ 21:38:28\n\nDextools | Dexscreener | Pump",
    "links": [
      "https://t.me/ApexSolanaSignal/14768",
      "https://dexscreener.com/solana/7CCeK4AZJQUxipj7vqGRo8d6pg6NDGiP1XMCdALFV5Bj",
      "https://www.pump.fun/7CCeK4AZJQUxipj7vqGRo8d6pg6NDGiP1XMCdALFV5Bj",
      "https://www.dextools.io/app/en/solana/pair-explorer/7CCeK4AZJQUxipj7vqGRo8d6pg6NDGiP1XMCdALFV5Bj",
      "https://solscan.io/token/7CCeK4AZJQUxipj7vqGRo8d6pg6NDGiP1XMCdALFV5Bj"
    ]
  },
  {
    "id": "465620",
    "date": "2025-05-14 21:38:44+00:00",
    "text": "$ABC (Always Be Coding) \n7CCeK4AZJQUxipj7vqGRo8d6pg6NDGiP1XMCdALFV5Bj\n\n💰 Marketcap: $250.61K\n\n🟢 CALLS - 2\n\n14 MAY (UTC)\n1. Apex Solana Signal \n└ 21:38:28\n2. 4AM Solana Volume Signal 🆕\n└ 21:38:42\n\nDextools | Dexscreener | Pump",
    "links": [
      "https://t.me/ApexSolanaSignal/14768",
      "https://dexscreener.com/solana/7CCeK4AZJQUxipj7vqGRo8d6pg6NDGiP1XMCdALFV5Bj",
      "https://www.pump.fun/7CCeK4AZJQUxipj7vqGRo8d6pg6NDGiP1XMCdALFV5Bj",
      "https://www.dextools.io/app/en/solana/pair-explorer/7CCeK4AZJQUxipj7vqGRo8d6pg6NDGiP1XMCdALFV5Bj",
      "https://t.me/signalsolanaby4am/75815",
      "https://solscan.io/token/7CCeK4AZJQUxipj7vqGRo8d6pg6NDGiP1XMCdALFV5Bj"
    ]
  },
  {
    "id": "465621",
    "date": "2025-05-14 21:39:00+00:00",
    "text": "$PLUG (PLUG  MCP Servers Hub) \nyPDpkFQQ6AvTQUfbSHMVvakqCX34VYKwoDrMb2Wbonk\n\n💰 Marketcap: $526.59K\n\n🟢 CALLS - 7\n\n14 MAY (UTC)\n1. Apex Solana Signal \n└ 20:40:47\n2. 4AM Solana Volume Signal \n└ 20:40:59\n3. Madness Call \n└ 20:49:02\n4. Ranma Calls - Solana \n└ 20:49:37\n5. OpalGems | Channel \n└ 20:50:02\n6. 🐋 Free Whale Signals 🐋 \n└ 20:51:05\n7. Goons Gems 𓃵 🆕\n└ 21:38:58\n\n🟢 Twitter | Website \n\nDextools | Dexscreener | Pump",
    "links": [
      "https://t.me/Ranma_Calls_Solana/17798",
      "https://www.dextools.io/app/en/solana/pair-explorer/yPDpkFQQ6AvTQUfbSHMVvakqCX34VYKwoDrMb2Wbonk",
      "https://t.me/ApexSolanaSignal/14645",
      "https://x.com/PlugMCP",
      "https://t.me/whaleBuyBotFree/5939",
      "https://dexscreener.com/solana/yPDpkFQQ6AvTQUfbSHMVvakqCX34VYKwoDrMb2Wbonk",
      "https://t.me/GoonsCalls/10618",
      "https://solscan.io/token/yPDpkFQQ6AvTQUfbSHMVvakqCX34VYKwoDrMb2Wbonk",
      "https://t.me/MadnessCall/21910",
      "https://www.plugmcp.live/",
      "https://t.me/OpalGemsCall/3833",
      "https://t.me/signalsolanaby4am/75767",
      "https://www.pump.fun/yPDpkFQQ6AvTQUfbSHMVvakqCX34VYKwoDrMb2Wbonk"
    ]
  },
  {
    "id": "465622",
    "date": "2025-05-14 21:39:10+00:00",
    "text": "$ABC (Always Be Coding) \n7CCeK4AZJQUxipj7vqGRo8d6pg6NDGiP1XMCdALFV5Bj\n\n💰 Marketcap: $204.94K\n\n🟢 CALLS - 3\n\n14 MAY (UTC)\n1. Apex Solana Signal \n└ 21:38:28\n2. 4AM Solana Volume Signal \n└ 21:38:42\n3. Madness Call 🆕\n└ 21:39:07\n\nDextools | Dexscreener | Pump",
    "links": [
      "https://t.me/ApexSolanaSignal/14768",
      "https://dexscreener.com/solana/7CCeK4AZJQUxipj7vqGRo8d6pg6NDGiP1XMCdALFV5Bj",
      "https://t.me/MadnessCall/21923",
      "https://www.pump.fun/7CCeK4AZJQUxipj7vqGRo8d6pg6NDGiP1XMCdALFV5Bj",
      "https://www.dextools.io/app/en/solana/pair-explorer/7CCeK4AZJQUxipj7vqGRo8d6pg6NDGiP1XMCdALFV5Bj",
      "https://t.me/signalsolanaby4am/75815",
      "https://solscan.io/token/7CCeK4AZJQUxipj7vqGRo8d6pg6NDGiP1XMCdALFV5Bj"
    ]
  },
  {
    "id": "465623",
    "date": "2025-05-14 21:39:21+00:00",
    "text": "💊 $LENS (LENS) \nAdwCEWQGzt3vuFMEPMf97AJMiq1eYL2sR7gk2x42pump\n\n💰 Marketcap: $3.09M\n\n🟢 CALLS - 8\n\n15 MAR (UTC)\n1. Savannah Wakanda ℗ \n└ 14:30:49\n2. 4AM Solana Volume Signal \n└ 20:48:19\n16 MAR (UTC)\n3. Apex Solana Signal \n└ 01:43:48\n4. Gems Mine \n└ 15:28:55\n17 MAR (UTC)\n5. Crypto Launch Hunter \n└ 08:26:25\n6. BlockChainBrothers Degen {BCB} \n└ 10:41:28\n20 MAR (UTC)\n7. The Mind Of Thanos \n└ 16:06:49\n14 MAY (UTC)\n8. ZODIGEM - BOT SIGNAL 🆕\n└ 21:39:16\n\n🟢 SOL TRENDING（Time of first appearance on SOL TRENDING.）\n2025-03-15 20:43:00 UTC\n\n🟢 Telegram | Twitter | Website \n\nDextools | Dexscreener | Pump",
    "links": [
      "https://t.me/MineGems/11974",
      "https://www.dextools.io/app/en/solana/pair-explorer/AdwCEWQGzt3vuFMEPMf97AJMiq1eYL2sR7gk2x42pump",
      "https://www.pump.fun/AdwCEWQGzt3vuFMEPMf97AJMiq1eYL2sR7gk2x42pump",
      "https://solscan.io/token/AdwCEWQGzt3vuFMEPMf97AJMiq1eYL2sR7gk2x42pump",
      "https://t.me/ZodiGemAlpha/8511",
      "https://x.com/getlensnow",
      "https://dexscreener.com/solana/AdwCEWQGzt3vuFMEPMf97AJMiq1eYL2sR7gk2x42pump",
      "https://t.me/Apexsol_bot/5158",
      "https://t.me/SAVANNAHCALLS/21419",
      "https://t.me/CryptoLaunchhunter/12322",
      "https://t.me/signalsolanaby4am/60418",
      "https://t.me/getlensnow",
      "https://t.me/thanos_mind/707",
      "https://getlensnow.com/",
      "https://t.me/BlockChainBrothersGambles/12682",
      "tg://resolve?domain=trendingssol"
    ]
  }
]