[
  {
    "id": "464235",
    "date": "2025-05-14 13:26:44+00:00",
    "text": "💊 $Analyze (Analyze.MCP) \nFzCwkFubpxZTkCK5PJAKbPSrWyxtXFkKx58XySNUpump\n\n💰 Marketcap: $130.65K\n\n🟢 CALLS - 6\n\n14 MAY (UTC)\n1. Degen's History \n└ 13:22:32\n2. AUTO 007 \n└ 13:23:47\n3. 4AM Pumpfun Volume Signal \n└ 13:23:51\n4. THE DEGEN BOYS \n└ 13:24:03\n5. Pumpfun Ultimate Alert \n└ 13:25:21\n6. PEPE CALLS 🆕\n└ 13:26:41\n\nAfter 48 sec of open trading, the first community call was initiated (promoted very early)\n\n🟢 Twitter | Website \n\nDextools | Dexscreener | Pump",
    "links": [
      "https://t.me/degenhistory/16889",
      "https://t.me/pfultimate/46877",
      "https://t.me/PEPE_Calls28/15671",
      "https://t.me/pumpfunvolumeby4AM/59689",
      "https://x.com/AnalyzeMCP",
      "https://www.dextools.io/app/en/solana/pair-explorer/FzCwkFubpxZTkCK5PJAKbPSrWyxtXFkKx58XySNUpump",
      "https://t.me/TheDegenBoysLounge/28344",
      "https://solscan.io/token/FzCwkFubpxZTkCK5PJAKbPSrWyxtXFkKx58XySNUpump",
      "https://t.me/auto007degen/42419",
      "https://www.analyzemcp.world/",
      "https://dexscreener.com/solana/FzCwkFubpxZTkCK5PJAKbPSrWyxtXFkKx58XySNUpump",
      "https://www.pump.fun/FzCwkFubpxZTkCK5PJAKbPSrWyxtXFkKx58XySNUpump"
    ]
  },
  {
    "id": "464236",
    "date": "2025-05-14 13:27:06+00:00",
    "text": "💊 $Analyze (Analyze.MCP) \nFzCwkFubpxZTkCK5PJAKbPSrWyxtXFkKx58XySNUpump\n\n💰 Marketcap: $152.26K\n\n🟢 CALLS - 7\n\n14 MAY (UTC)\n1. Degen's History \n└ 13:22:32\n2. AUTO 007 \n└ 13:23:47\n3. 4AM Pumpfun Volume Signal \n└ 13:23:51\n4. THE DEGEN BOYS \n└ 13:24:03\n5. Pumpfun Ultimate Alert \n└ 13:25:21\n6. PEPE CALLS \n└ 13:26:41\n7. Apex Solana Signal 🆕\n└ 13:27:00\n\nAfter 48 sec of open trading, the first community call was initiated (promoted very early)\n\n🟢 Twitter | Website \n\nDextools | Dexscreener | Pump",
    "links": [
      "https://t.me/degenhistory/16889",
      "https://t.me/pfultimate/46877",
      "https://t.me/PEPE_Calls28/15671",
      "https://t.me/pumpfunvolumeby4AM/59689",
      "https://t.me/ApexSolanaSignal/14104",
      "https://x.com/AnalyzeMCP",
      "https://t.me/TheDegenBoysLounge/28344",
      "https://solscan.io/token/FzCwkFubpxZTkCK5PJAKbPSrWyxtXFkKx58XySNUpump",
      "https://t.me/auto007degen/42419",
      "https://www.analyzemcp.world/",
      "https://www.dextools.io/app/en/solana/pair-explorer/FzCwkFubpxZTkCK5PJAKbPSrWyxtXFkKx58XySNUpump",
      "https://dexscreener.com/solana/FzCwkFubpxZTkCK5PJAKbPSrWyxtXFkKx58XySNUpump",
      "https://www.pump.fun/FzCwkFubpxZTkCK5PJAKbPSrWyxtXFkKx58XySNUpump"
    ]
  },
  {
    "id": "464237",
    "date": "2025-05-14 13:27:15+00:00",
    "text": "💊 $Analyze (Analyze.MCP) \nFzCwkFubpxZTkCK5PJAKbPSrWyxtXFkKx58XySNUpump\n\n💰 Marketcap: $140.80K\n\n🟢 CALLS - 8\n\n14 MAY (UTC)\n1. Degen's History \n└ 13:22:32\n2. AUTO 007 \n└ 13:23:47\n3. 4AM Pumpfun Volume Signal \n└ 13:23:51\n4. THE DEGEN BOYS \n└ 13:24:03\n5. Pumpfun Ultimate Alert \n└ 13:25:21\n6. PEPE CALLS \n└ 13:26:41\n7. Apex Solana Signal \n└ 13:27:00\n8. Kingdom of Degen CALLS 🆕\n└ 13:27:12\n\nAfter 48 sec of open trading, the first community call was initiated (promoted very early)\n\n🟢 Twitter | Website \n\nDextools | Dexscreener | Pump",
    "links": [
      "https://t.me/degenhistory/16889",
      "https://t.me/KingdomOfDegenCalls/51634",
      "https://t.me/pfultimate/46877",
      "https://t.me/PEPE_Calls28/15671",
      "https://t.me/pumpfunvolumeby4AM/59689",
      "https://t.me/ApexSolanaSignal/14104",
      "https://x.com/AnalyzeMCP",
      "https://t.me/TheDegenBoysLounge/28344",
      "https://solscan.io/token/FzCwkFubpxZTkCK5PJAKbPSrWyxtXFkKx58XySNUpump",
      "https://t.me/auto007degen/42419",
      "https://www.analyzemcp.world/",
      "https://www.dextools.io/app/en/solana/pair-explorer/FzCwkFubpxZTkCK5PJAKbPSrWyxtXFkKx58XySNUpump",
      "https://dexscreener.com/solana/FzCwkFubpxZTkCK5PJAKbPSrWyxtXFkKx58XySNUpump",
      "https://www.pump.fun/FzCwkFubpxZTkCK5PJAKbPSrWyxtXFkKx58XySNUpump"
    ]
  },
  {
    "id": "464238",
    "date": "2025-05-14 13:27:28+00:00",
    "text": "💊 $Analyze (Analyze.MCP) \nFzCwkFubpxZTkCK5PJAKbPSrWyxtXFkKx58XySNUpump\n\n💰 Marketcap: $136.67K\n\n🟢 CALLS - 9\n\n14 MAY (UTC)\n1. Degen's History \n└ 13:22:32\n2. AUTO 007 \n└ 13:23:47\n3. 4AM Pumpfun Volume Signal \n└ 13:23:51\n4. THE DEGEN BOYS \n└ 13:24:03\n5. Pumpfun Ultimate Alert \n└ 13:25:21\n6. PEPE CALLS \n└ 13:26:41\n7. Apex Solana Signal \n└ 13:27:00\n8. Kingdom of Degen CALLS \n└ 13:27:12\n9. 4AM Solana Volume Signal 🆕\n└ 13:27:25\n\nAfter 48 sec of open trading, the first community call was initiated (promoted very early)\n\n🟢 Twitter | Website \n\nDextools | Dexscreener | Pump",
    "links": [
      "https://t.me/signalsolanaby4am/75479",
      "https://t.me/degenhistory/16889",
      "https://t.me/KingdomOfDegenCalls/51634",
      "https://t.me/pfultimate/46877",
      "https://t.me/PEPE_Calls28/15671",
      "https://t.me/pumpfunvolumeby4AM/59689",
      "https://t.me/ApexSolanaSignal/14104",
      "https://x.com/AnalyzeMCP",
      "https://t.me/TheDegenBoysLounge/28344",
      "https://solscan.io/token/FzCwkFubpxZTkCK5PJAKbPSrWyxtXFkKx58XySNUpump",
      "https://t.me/auto007degen/42419",
      "https://www.analyzemcp.world/",
      "https://www.dextools.io/app/en/solana/pair-explorer/FzCwkFubpxZTkCK5PJAKbPSrWyxtXFkKx58XySNUpump",
      "https://dexscreener.com/solana/FzCwkFubpxZTkCK5PJAKbPSrWyxtXFkKx58XySNUpump",
      "https://www.pump.fun/FzCwkFubpxZTkCK5PJAKbPSrWyxtXFkKx58XySNUpump"
    ]
  },
  {
    "id": "464239",
    "date": "2025-05-14 13:28:12+00:00",
    "text": "🧪 $RONK (ケン RONK) \n5t4pZVTsR6KS1VYDsUuGo2bcvfwBZqR2z4NRU4jtbonk\n\n💰 Marketcap: $23.43K\n\nCALLS - 1\n\n14 MAY (UTC)\n1. Memes Don’t Lies 🆕\n└ 13:28:10\n\n🟢 Twitter | Website \n\nDextools | Dexscreener | LaunchLab",
    "links": [
      "https://solscan.io/token/5t4pZVTsR6KS1VYDsUuGo2bcvfwBZqR2z4NRU4jtbonk",
      "https://dexscreener.com/solana/5t4pZVTsR6KS1VYDsUuGo2bcvfwBZqR2z4NRU4jtbonk",
      "https://t.me/MemesDontLies/96339",
      "https://x.com/GrokSlack/status/1922644631721771157",
      "https://www.dextools.io/app/en/solana/pair-explorer/5t4pZVTsR6KS1VYDsUuGo2bcvfwBZqR2z4NRU4jtbonk",
      "https://raydium.io/launchpad/token/?mint=5t4pZVTsR6KS1VYDsUuGo2bcvfwBZqR2z4NRU4jtbonk",
      "https://starfy.fandom.com/wiki/Ronk"
    ]
  }
]