[
  {
    "id": "460352",
    "date": "2025-05-12 19:49:25+00:00",
    "text": "💊 $Cycle (Cycle) \nHJ2n2a3YK1LTBCRbS932cTtmXw4puhgG8Jb2WcpEpump\n\n💰 Marketcap: $59.80K\n\n🟢 CALLS - 4\n\n12 MAY (UTC)\n1. Degen's History \n└ 19:45:41\n2. Savannah Wakanda ℗ \n└ 19:48:41\n3. Pumpfun Ultimate Alert \n└ 19:49:07\n4. 4AM Pumpfun Volume Signal 🆕\n└ 19:49:20\n\nAfter ＜ 1min of open trading, the first community call was initiated (promoted very early)\n\n🟢 Twitter | Website \n\nDextools | Dexscreener | Pump",
    "links": [
      "https://www.pump.fun/HJ2n2a3YK1LTBCRbS932cTtmXw4puhgG8Jb2WcpEpump",
      "https://solscan.io/token/HJ2n2a3YK1LTBCRbS932cTtmXw4puhgG8Jb2WcpEpump",
      "https://cyclesol.dev/",
      "https://t.me/degenhistory/16612",
      "https://dexscreener.com/solana/HJ2n2a3YK1LTBCRbS932cTtmXw4puhgG8Jb2WcpEpump",
      "https://t.me/SAVANNAHCALLS/40842",
      "https://t.me/pumpfunvolumeby4AM/58972",
      "https://t.me/pfultimate/46435",
      "https://x.com/cycleonsolana",
      "https://www.dextools.io/app/en/solana/pair-explorer/HJ2n2a3YK1LTBCRbS932cTtmXw4puhgG8Jb2WcpEpump"
    ]
  },
  {
    "id": "460353",
    "date": "2025-05-12 19:49:26+00:00",
    "text": "💊 $ (PUMPFUN PILLHEAD CULT (PILLHEAD) \nGMhfqTnre4DnPKk74X2EGTHhicuP61PYdAeVYNzWpump\n\n💰 Marketcap: $35.78K\n\nCALLS - 1\n\n12 MAY (UTC)\n1. Moo Deng President 🆕\n└ 19:49:21\n\n♻️ Twitter Username History\n🕑 4d ago ⋅ pumpdotfun\n\n🟢 Twitter | Website \n\nDextools | Dexscreener | Pump\n\n👉 Experience Dogee on BSC for Lightning-Fast Copy Trading",
    "links": [
      "https://dexscreener.com/solana/GMhfqTnre4DnPKk74X2EGTHhicuP61PYdAeVYNzWpump",
      "https://www.dextools.io/app/en/solana/pair-explorer/GMhfqTnre4DnPKk74X2EGTHhicuP61PYdAeVYNzWpump",
      "https://solscan.io/token/GMhfqTnre4DnPKk74X2EGTHhicuP61PYdAeVYNzWpump",
      "https://x.com/pumpdotfun/status/1819491124525814089",
      "https://t.me/MooDengPresidentCallers/59577",
      "https://t.me/dogeebsc_bot?start=inv-1524500950"
    ]
  },
  {
    "id": "460354",
    "date": "2025-05-12 19:49:29+00:00",
    "text": "💊 $Cycle (Cycle) \nHJ2n2a3YK1LTBCRbS932cTtmXw4puhgG8Jb2WcpEpump\n\n💰 Marketcap: $84.24K\n\n🟢 CALLS - 5\n\n12 MAY (UTC)\n1. Degen's History \n└ 19:45:41\n2. Savannah Wakanda ℗ \n└ 19:48:41\n3. Pumpfun Ultimate Alert \n└ 19:49:07\n4. 4AM Pumpfun Volume Signal \n└ 19:49:20\n5. THE DEGEN BOYS 🆕\n└ 19:49:26\n\nAfter 2 sec of open trading, the first community call was initiated (promoted very early)\n\n🟢 Twitter | Website \n\nDextools | Dexscreener | Pump\n\n👉 Experience Dogee on BSC for Lightning-Fast Copy Trading",
    "links": [
      "https://www.pump.fun/HJ2n2a3YK1LTBCRbS932cTtmXw4puhgG8Jb2WcpEpump",
      "https://solscan.io/token/HJ2n2a3YK1LTBCRbS932cTtmXw4puhgG8Jb2WcpEpump",
      "https://t.me/dogeebsc_bot?start=inv-1524500950",
      "https://cyclesol.dev/",
      "https://t.me/degenhistory/16612",
      "https://t.me/TheDegenBoysLounge/28038",
      "https://dexscreener.com/solana/HJ2n2a3YK1LTBCRbS932cTtmXw4puhgG8Jb2WcpEpump",
      "https://t.me/SAVANNAHCALLS/40842",
      "https://t.me/pumpfunvolumeby4AM/58972",
      "https://t.me/pfultimate/46435",
      "https://x.com/cycleonsolana",
      "https://www.dextools.io/app/en/solana/pair-explorer/HJ2n2a3YK1LTBCRbS932cTtmXw4puhgG8Jb2WcpEpump"
    ]
  },
  {
    "id": "460355",
    "date": "2025-05-12 19:49:51+00:00",
    "text": "$SING (SING) \n6S9sEpVTunuyJYsaXwsVpVxtJZff8V9nW3j2sDrcbonk\n\n💰 Marketcap: $140.81K\n\n🟢 CALLS - 2\n\n12 MAY (UTC)\n1. Apex Solana Signal \n└ 19:47:19\n2. SolHouse Signal 🆕\n└ 19:49:46\n\n🟢 Twitter | Website \n\nDextools | Dexscreener | Pump",
    "links": [
      "https://t.me/solhousesignal/51078",
      "https://www.pump.fun/6S9sEpVTunuyJYsaXwsVpVxtJZff8V9nW3j2sDrcbonk",
      "https://x.com/AurisSings",
      "https://t.me/ApexSolanaSignal/11863",
      "https://www.aurissings.com/",
      "https://dexscreener.com/solana/6S9sEpVTunuyJYsaXwsVpVxtJZff8V9nW3j2sDrcbonk",
      "https://solscan.io/token/6S9sEpVTunuyJYsaXwsVpVxtJZff8V9nW3j2sDrcbonk",
      "https://www.dextools.io/app/en/solana/pair-explorer/6S9sEpVTunuyJYsaXwsVpVxtJZff8V9nW3j2sDrcbonk"
    ]
  },
  {
    "id": "460356",
    "date": "2025-05-12 19:49:55+00:00",
    "text": "$SING (SING) \n6S9sEpVTunuyJYsaXwsVpVxtJZff8V9nW3j2sDrcbonk\n\n💰 Marketcap: $144.75K\n\n🟢 CALLS - 3\n\n12 MAY (UTC)\n1. Apex Solana Signal \n└ 19:47:19\n2. SolHouse Signal \n└ 19:49:46\n3. Ranma Calls - Solana 🆕\n└ 19:49:52\n\n🟢 Twitter | Website \n\nDextools | Dexscreener | Pump\n\n👉 Experience Dogee on BSC for Lightning-Fast Copy Trading",
    "links": [
      "https://t.me/solhousesignal/51078",
      "https://t.me/dogeebsc_bot?start=inv-1524500950",
      "https://www.pump.fun/6S9sEpVTunuyJYsaXwsVpVxtJZff8V9nW3j2sDrcbonk",
      "https://x.com/AurisSings",
      "https://t.me/ApexSolanaSignal/11863",
      "https://www.aurissings.com/",
      "https://dexscreener.com/solana/6S9sEpVTunuyJYsaXwsVpVxtJZff8V9nW3j2sDrcbonk",
      "https://solscan.io/token/6S9sEpVTunuyJYsaXwsVpVxtJZff8V9nW3j2sDrcbonk",
      "https://t.me/Ranma_Calls_Solana/17256",
      "https://www.dextools.io/app/en/solana/pair-explorer/6S9sEpVTunuyJYsaXwsVpVxtJZff8V9nW3j2sDrcbonk"
    ]
  }
]