[
  {
    "id": "460045",
    "date": "2025-05-12 17:25:23+00:00",
    "text": "💊 $pump (pumpdog) \n9jFDHjAZuLhkrF2BivDs9BVzb6Lg6pYSuRiuCrHtpump\n\n💰 Marketcap: $146.33K\n\n🟢 CALLS - 18\n\n12 MAY (UTC)\n1. Degen's History \n└ 17:05:33\n2. Memes Don’t Lies \n└ 17:07:49\n3. Pumpfun Ultimate Alert \n└ 17:08:47\n4. Savannah Wakanda ℗ \n└ 17:09:43\n5. Pump.fun Premium Call 💊 \n└ 17:09:55\n6. TUBOR DEGEN CALLS \n└ 17:10:43\n7. ZODIGEM - BOT SIGNAL \n└ 17:10:51\n8. Ranma Calls - Solana \n└ 17:10:57\n9. OxyZen Calls \n└ 17:11:51\n10. 🚨 SHITCOIN GEMS ALERT 🚨 \n└ 17:12:54\n11. Kingdom of Degen CALLS \n└ 17:14:09\n12. OpalGems | Channel \n└ 17:14:53\n13. Apex Solana Signal \n└ 17:15:12\n14. 4AM Solana Volume Signal \n└ 17:15:18\n15. WOOF CALLS 🐺💎 \n└ 17:15:55\n16. Madness Call \n└ 17:17:10\n17. MEDUSA CALL \n└ 17:25:02\n18. BASED DEGEN GEMS 🆕\n└ 17:25:19\n\nAfter 3 sec of open trading, the first community call was initiated (promoted very early)\n\n🟢 Twitter | Website \n\nDextools | Dexscreener | Pump",
    "links": [
      "https://t.me/pfultimate/46403",
      "https://t.me/ApexSolanaSignal/11777",
      "https://t.me/SAVANNAHCALLS/40791",
      "https://pump.fun/coin/9jFDHjAZuLhkrF2BivDs9BVzb6Lg6pYSuRiuCrHtpump",
      "https://t.me/MadnessCall/21831",
      "https://x.com/search?q=pumpdog&src=typed_query",
      "https://t.me/shitcoingemsalert/61880",
      "https://t.me/WOOF_CALL/1543",
      "https://t.me/Ranma_Calls_Solana/17227",
      "https://t.me/MemesDontLies/96122",
      "https://t.me/degenhistory/16586",
      "https://www.pump.fun/9jFDHjAZuLhkrF2BivDs9BVzb6Lg6pYSuRiuCrHtpump",
      "https://t.me/signalsolanaby4am/74427",
      "https://t.me/hulkgemscalls_real/8254",
      "https://t.me/BasedDegenGems/13019",
      "https://t.me/KingdomOfDegenCalls/51353",
      "https://t.me/medusacalll/1182",
      "https://solscan.io/token/9jFDHjAZuLhkrF2BivDs9BVzb6Lg6pYSuRiuCrHtpump",
      "https://t.me/ZodiGemAlpha/7980",
      "https://dexscreener.com/solana/9jFDHjAZuLhkrF2BivDs9BVzb6Lg6pYSuRiuCrHtpump",
      "https://www.dextools.io/app/en/solana/pair-explorer/9jFDHjAZuLhkrF2BivDs9BVzb6Lg6pYSuRiuCrHtpump",
      "https://t.me/Zen_call/20959",
      "https://t.me/Pumpfunpremium/19567",
      "https://t.me/OpalGemsCall/3603"
    ]
  },
  {
    "id": "460046",
    "date": "2025-05-12 17:25:36+00:00",
    "text": "💊 $TrumpPoint (Justice for TrumpPoints) \nEh8KXT8U1z5m82cLanZVsJKmvQYEE9QPqfYYzFSapump\n\n💰 Marketcap: $38.94K\n\n🟢 CALLS - 3\n\n12 MAY (UTC)\n1. NASA DEGEN CALLS \n└ 17:18:29\n2. 4AM Pumpfun Volume Signal \n└ 17:25:07\n3. Savannah Wakanda ℗ 🆕\n└ 17:25:32\n\n🟢 Website \n\nDextools | Dexscreener | Pump",
    "links": [
      "https://t.me/pumpfunvolumeby4AM/58930",
      "https://dexscreener.com/solana/Eh8KXT8U1z5m82cLanZVsJKmvQYEE9QPqfYYzFSapump",
      "https://t.me/NASAVIP8SPACESHIP/7633",
      "https://t.me/SAVANNAHCALLS/40798",
      "https://trumppoints.gettrumpmemes.com/listings",
      "https://www.pump.fun/Eh8KXT8U1z5m82cLanZVsJKmvQYEE9QPqfYYzFSapump",
      "https://www.dextools.io/app/en/solana/pair-explorer/Eh8KXT8U1z5m82cLanZVsJKmvQYEE9QPqfYYzFSapump",
      "https://solscan.io/token/Eh8KXT8U1z5m82cLanZVsJKmvQYEE9QPqfYYzFSapump"
    ]
  },
  {
    "id": "460047",
    "date": "2025-05-12 17:25:51+00:00",
    "text": "💊 $TrumpPoint (Justice for TrumpPoints) \nEh8KXT8U1z5m82cLanZVsJKmvQYEE9QPqfYYzFSapump\n\n💰 Marketcap: $25.75K\n\n🟢 CALLS - 4\n\n12 MAY (UTC)\n1. NASA DEGEN CALLS \n└ 17:18:29\n2. 4AM Pumpfun Volume Signal \n└ 17:25:07\n3. Savannah Wakanda ℗ \n└ 17:25:32\n4. THE DEGEN BOYS 🆕\n└ 17:25:48\n\n🟢 Website \n\nDextools | Dexscreener | Pump",
    "links": [
      "https://t.me/pumpfunvolumeby4AM/58930",
      "https://dexscreener.com/solana/Eh8KXT8U1z5m82cLanZVsJKmvQYEE9QPqfYYzFSapump",
      "https://t.me/NASAVIP8SPACESHIP/7633",
      "https://t.me/SAVANNAHCALLS/40798",
      "https://trumppoints.gettrumpmemes.com/listings",
      "https://www.pump.fun/Eh8KXT8U1z5m82cLanZVsJKmvQYEE9QPqfYYzFSapump",
      "https://www.dextools.io/app/en/solana/pair-explorer/Eh8KXT8U1z5m82cLanZVsJKmvQYEE9QPqfYYzFSapump",
      "https://solscan.io/token/Eh8KXT8U1z5m82cLanZVsJKmvQYEE9QPqfYYzFSapump",
      "https://t.me/TheDegenBoysLounge/28006"
    ]
  },
  {
    "id": "460048",
    "date": "2025-05-12 17:27:23+00:00",
    "text": "$ () \nDWMCN4mgauSRPDLYmToq7BjYyLAqVdfhztuexU2qaXtD\n\n🟡 PRELAUNCH CALLS - 1\n\n12 MAY (UTC)\n1. Degen's History 🆕\n└ 17:27:20\n\nDextools | Dexscreener | Pump",
    "links": [
      "https://www.dextools.io/app/en/solana/pair-explorer/DWMCN4mgauSRPDLYmToq7BjYyLAqVdfhztuexU2qaXtD",
      "https://solscan.io/token/DWMCN4mgauSRPDLYmToq7BjYyLAqVdfhztuexU2qaXtD",
      "https://dexscreener.com/solana/DWMCN4mgauSRPDLYmToq7BjYyLAqVdfhztuexU2qaXtD",
      "https://www.pump.fun/DWMCN4mgauSRPDLYmToq7BjYyLAqVdfhztuexU2qaXtD",
      "https://t.me/degenhistory/16593"
    ]
  },
  {
    "id": "460049",
    "date": "2025-05-12 17:27:45+00:00",
    "text": "💊 $TRUMP (IN TRUMP WE TRUST) \n8b7dSWJLAjxkWhTGAZry41ovFq1rwswXWutaBxoqpump\n\n💰 Marketcap: $26.24K\n\nCALLS - 1\n\n12 MAY (UTC)\n1. Memes Don’t Lies 🆕\n└ 17:27:42\n\n♻️ Twitter Username History\n🕑 2mo ago ⋅ housegop\n\n🟢 Twitter | Website \n\nDextools | Dexscreener | Pump",
    "links": [
      "https://www.dextools.io/app/en/solana/pair-explorer/8b7dSWJLAjxkWhTGAZry41ovFq1rwswXWutaBxoqpump",
      "https://x.com/HouseGOP/status/1921979993388642665",
      "https://solscan.io/token/8b7dSWJLAjxkWhTGAZry41ovFq1rwswXWutaBxoqpump",
      "https://dexscreener.com/solana/8b7dSWJLAjxkWhTGAZry41ovFq1rwswXWutaBxoqpump",
      "https://t.me/MemesDontLies/96132"
    ]
  }
]