[
  {
    "id": "464704",
    "date": "2025-05-14 16:02:12+00:00",
    "text": "💊 $IDC (Infinite Donations Coin) \nBCb8VEPakUrDi1X3f7YZAMyQoXZsGDAfzhJZmMqppump\n\n💰 Marketcap: $41.11K\n\nCALLS - 1\n\n14 MAY (UTC)\n1. Degen's History 🆕\n└ 16:02:10\n\n🟢 Twitter \n\nDextools | Dexscreener | Pump",
    "links": [
      "https://solscan.io/token/BCb8VEPakUrDi1X3f7YZAMyQoXZsGDAfzhJZmMqppump",
      "https://t.me/degenhistory/16914",
      "https://www.dextools.io/app/en/solana/pair-explorer/BCb8VEPakUrDi1X3f7YZAMyQoXZsGDAfzhJZmMqppump",
      "https://dexscreener.com/solana/BCb8VEPakUrDi1X3f7YZAMyQoXZsGDAfzhJZmMqppump",
      "https://x.com/IDCoinSOL"
    ]
  },
  {
    "id": "464705",
    "date": "2025-05-14 16:02:17+00:00",
    "text": "💊 $IDC (Infinite Donations Coin) \nBCb8VEPakUrDi1X3f7YZAMyQoXZsGDAfzhJZmMqppump\n\n💰 Marketcap: $37.31K\n\n🟢 CALLS - 2\n\n14 MAY (UTC)\n1. Degen's History \n└ 16:02:10\n2. AUTO 007 🆕\n└ 16:02:15\n\n🟢 Twitter \n\nDextools | Dexscreener | Pump",
    "links": [
      "https://www.pump.fun/BCb8VEPakUrDi1X3f7YZAMyQoXZsGDAfzhJZmMqppump",
      "https://t.me/auto007degen/42446",
      "https://solscan.io/token/BCb8VEPakUrDi1X3f7YZAMyQoXZsGDAfzhJZmMqppump",
      "https://t.me/degenhistory/16914",
      "https://www.dextools.io/app/en/solana/pair-explorer/BCb8VEPakUrDi1X3f7YZAMyQoXZsGDAfzhJZmMqppump",
      "https://dexscreener.com/solana/BCb8VEPakUrDi1X3f7YZAMyQoXZsGDAfzhJZmMqppump",
      "https://x.com/IDCoinSOL"
    ]
  },
  {
    "id": "464706",
    "date": "2025-05-14 16:02:40+00:00",
    "text": "💊 $IDC (Infinite Donations Coin) \nBCb8VEPakUrDi1X3f7YZAMyQoXZsGDAfzhJZmMqppump\n\n💰 Marketcap: $34.67K\n\n🟢 CALLS - 3\n\n14 MAY (UTC)\n1. Degen's History \n└ 16:02:10\n2. AUTO 007 \n└ 16:02:15\n3. 4AM Pumpfun Volume Signal 🆕\n└ 16:02:20\n\n🟢 Twitter \n\nDextools | Dexscreener | Pump",
    "links": [
      "https://www.pump.fun/BCb8VEPakUrDi1X3f7YZAMyQoXZsGDAfzhJZmMqppump",
      "https://t.me/auto007degen/42446",
      "https://solscan.io/token/BCb8VEPakUrDi1X3f7YZAMyQoXZsGDAfzhJZmMqppump",
      "https://t.me/pumpfunvolumeby4AM/59777",
      "https://t.me/degenhistory/16914",
      "https://www.dextools.io/app/en/solana/pair-explorer/BCb8VEPakUrDi1X3f7YZAMyQoXZsGDAfzhJZmMqppump",
      "https://dexscreener.com/solana/BCb8VEPakUrDi1X3f7YZAMyQoXZsGDAfzhJZmMqppump",
      "https://x.com/IDCoinSOL"
    ]
  },
  {
    "id": "464707",
    "date": "2025-05-14 16:02:41+00:00",
    "text": "💊 $IDC (Infinite Donations Coin) \nBCb8VEPakUrDi1X3f7YZAMyQoXZsGDAfzhJZmMqppump\n\n💰 Marketcap: $36.23K\n\n🟢 CALLS - 4\n\n14 MAY (UTC)\n1. Degen's History \n└ 16:02:10\n2. AUTO 007 \n└ 16:02:15\n3. 4AM Pumpfun Volume Signal \n└ 16:02:20\n4. Savannah Wakanda ℗ 🆕\n└ 16:02:27\n\n🟢 Twitter \n\nDextools | Dexscreener | Pump\n\n👉 Experience Dogee on BSC for Lightning-Fast Copy Trading",
    "links": [
      "https://www.pump.fun/BCb8VEPakUrDi1X3f7YZAMyQoXZsGDAfzhJZmMqppump",
      "https://t.me/auto007degen/42446",
      "https://solscan.io/token/BCb8VEPakUrDi1X3f7YZAMyQoXZsGDAfzhJZmMqppump",
      "https://t.me/pumpfunvolumeby4AM/59777",
      "https://t.me/dogeebsc_bot?start=inv-1524500950",
      "https://t.me/degenhistory/16914",
      "https://www.dextools.io/app/en/solana/pair-explorer/BCb8VEPakUrDi1X3f7YZAMyQoXZsGDAfzhJZmMqppump",
      "https://dexscreener.com/solana/BCb8VEPakUrDi1X3f7YZAMyQoXZsGDAfzhJZmMqppump",
      "https://t.me/SAVANNAHCALLS/41504",
      "https://x.com/IDCoinSOL"
    ]
  },
  {
    "id": "464708",
    "date": "2025-05-14 16:03:03+00:00",
    "text": "$Willow (Willow) \nEGj1w7qe6KtMB1UhEZVPtisJag29yT44wTUKRLs3bonk\n\n💰 Marketcap: $171.63K\n\n🟢 CALLS - 3\n\n14 MAY (UTC)\n1. Memes Don’t Lies \n└ 15:49:53\n2. SolHouse Signal \n└ 16:01:47\n3. Crypto Mafia Plays 🆕\n└ 16:02:55\n\n🟢 Twitter | Website \n\nDextools | Dexscreener | Pump",
    "links": [
      "https://dexscreener.com/solana/EGj1w7qe6KtMB1UhEZVPtisJag29yT44wTUKRLs3bonk",
      "https://w1llow.com/",
      "https://x.com/Wi11l0w",
      "https://t.me/CryptoMafiaPlays/13199",
      "https://www.pump.fun/EGj1w7qe6KtMB1UhEZVPtisJag29yT44wTUKRLs3bonk",
      "https://www.dextools.io/app/en/solana/pair-explorer/EGj1w7qe6KtMB1UhEZVPtisJag29yT44wTUKRLs3bonk",
      "https://solscan.io/token/EGj1w7qe6KtMB1UhEZVPtisJag29yT44wTUKRLs3bonk",
      "https://t.me/solhousesignal/51712",
      "https://t.me/MemesDontLies/96415"
    ]
  }
]