[
  {
    "id": "464981",
    "date": "2025-05-14 17:51:17+00:00",
    "text": "💊 $500 (ASS&P 500 (ASS&P) \nFRUnVTbSteDWYmn8URfsJkHYgfu9MDxjz7vwYj4fpump\n\n💰 Marketcap: $39.79K\n\n🟢 CALLS - 5\n\n14 MAY (UTC)\n1. Solsta's Shills \n└ 17:43:53\n2. Degen's History \n└ 17:50:42\n3. 4AM Pumpfun Volume Signal \n└ 17:50:53\n4. Memes Don’t Lies \n└ 17:51:08\n5. THE DEGEN BOYS 🆕\n└ 17:51:14\n\nDextools | Dexscreener | Pump\n\n👉 Experience Dogee on BSC for Lightning-Fast Copy Trading",
    "links": [
      "https://www.dextools.io/app/en/solana/pair-explorer/FRUnVTbSteDWYmn8URfsJkHYgfu9MDxjz7vwYj4fpump",
      "https://t.me/SolstasShills/9151",
      "https://t.me/TheDegenBoysLounge/28392",
      "https://t.me/pumpfunvolumeby4AM/59828",
      "https://t.me/dogeebsc_bot?start=inv-1524500950",
      "https://t.me/MemesDontLies/96440",
      "https://t.me/degenhistory/16932",
      "https://dexscreener.com/solana/FRUnVTbSteDWYmn8URfsJkHYgfu9MDxjz7vwYj4fpump",
      "https://solscan.io/token/FRUnVTbSteDWYmn8URfsJkHYgfu9MDxjz7vwYj4fpump",
      "https://www.pump.fun/FRUnVTbSteDWYmn8URfsJkHYgfu9MDxjz7vwYj4fpump"
    ]
  },
  {
    "id": "464982",
    "date": "2025-05-14 17:52:15+00:00",
    "text": "💊 $PLB (Pretty Little Baby) \nFWqn2cpgefgQ9vwpjbNLMZXwQahbumHkxD9T6VLcpump\n\n💰 Marketcap: $34.18K\n\nCALLS - 1\n\n14 MAY (UTC)\n1. Degen's History 🆕\n└ 17:52:10\n\n🟢 Twitter | Website \n\nDextools | Dexscreener | Pump",
    "links": [
      "https://solscan.io/token/FWqn2cpgefgQ9vwpjbNLMZXwQahbumHkxD9T6VLcpump",
      "https://dexscreener.com/solana/FWqn2cpgefgQ9vwpjbNLMZXwQahbumHkxD9T6VLcpump",
      "https://x.com/i/communities/1922696772775710994/",
      "https://www.tiktok.com/search/video?q=pretty%20little%20baby&t=1747238789734",
      "https://www.dextools.io/app/en/solana/pair-explorer/FWqn2cpgefgQ9vwpjbNLMZXwQahbumHkxD9T6VLcpump",
      "https://t.me/degenhistory/16933"
    ]
  },
  {
    "id": "464983",
    "date": "2025-05-14 17:52:54+00:00",
    "text": "💊 $hearthands (Diddy Emote) \n5vNR2AErNd7J57nd1FTMMAkD7BiQvFuhYChEwRa1pump\n\n💰 Marketcap: $47.22K\n\n🟢 CALLS - 7\n\n14 MAY (UTC)\n1. Degen's History \n└ 17:48:18\n2. Moo Deng President \n└ 17:48:32\n3. 4AM Pumpfun Volume Signal \n└ 17:49:11\n4. Savannah Wakanda ℗ \n└ 17:49:20\n5. THE DEGEN BOYS \n└ 17:49:28\n6. Memes Don’t Lies \n└ 17:50:04\n7. Pumpfun Ultimate Alert 🆕\n└ 17:52:50\n\n🟢 Website \n\nDextools | Dexscreener | Pump",
    "links": [
      "https://solscan.io/token/5vNR2AErNd7J57nd1FTMMAkD7BiQvFuhYChEwRa1pump",
      "https://t.me/degenhistory/16931",
      "https://x.com/AutismCapital/status/1922684059592897009",
      "https://www.dextools.io/app/en/solana/pair-explorer/5vNR2AErNd7J57nd1FTMMAkD7BiQvFuhYChEwRa1pump",
      "https://t.me/pumpfunvolumeby4AM/59827",
      "https://www.pump.fun/5vNR2AErNd7J57nd1FTMMAkD7BiQvFuhYChEwRa1pump",
      "https://t.me/TheDegenBoysLounge/28391",
      "https://t.me/MemesDontLies/96439",
      "https://t.me/MooDengPresidentCallers/59977",
      "https://t.me/SAVANNAHCALLS/41536",
      "https://t.me/pfultimate/46935",
      "https://dexscreener.com/solana/5vNR2AErNd7J57nd1FTMMAkD7BiQvFuhYChEwRa1pump"
    ]
  },
  {
    "id": "464984",
    "date": "2025-05-14 17:52:57+00:00",
    "text": "💊 $PLB (Pretty Little Baby) \nFWqn2cpgefgQ9vwpjbNLMZXwQahbumHkxD9T6VLcpump\n\n💰 Marketcap: $34.46K\n\n🟢 CALLS - 2\n\n14 MAY (UTC)\n1. Degen's History \n└ 17:52:10\n2. Moo Deng President 🆕\n└ 17:52:55\n\n🟢 Twitter | Website \n\nDextools | Dexscreener | Pump",
    "links": [
      "https://solscan.io/token/FWqn2cpgefgQ9vwpjbNLMZXwQahbumHkxD9T6VLcpump",
      "https://dexscreener.com/solana/FWqn2cpgefgQ9vwpjbNLMZXwQahbumHkxD9T6VLcpump",
      "https://www.pump.fun/FWqn2cpgefgQ9vwpjbNLMZXwQahbumHkxD9T6VLcpump",
      "https://x.com/i/communities/1922696772775710994/",
      "https://www.tiktok.com/search/video?q=pretty%20little%20baby&t=1747238789734",
      "https://t.me/MooDengPresidentCallers/59980",
      "https://www.dextools.io/app/en/solana/pair-explorer/FWqn2cpgefgQ9vwpjbNLMZXwQahbumHkxD9T6VLcpump",
      "https://t.me/degenhistory/16933"
    ]
  },
  {
    "id": "464985",
    "date": "2025-05-14 17:53:09+00:00",
    "text": "💊 $PSOL (Phantom Sol) \n8Bf9y8ZjWA1CUhbrFtE74TpsGuwWnC7aMp6AY3ppump\n\n💰 Marketcap: $63.37K\n\nCALLS - 1\n\n14 MAY (UTC)\n1. AUTO 007 🆕\n└ 17:53:08\n\nAfter 29 sec of open trading, the first community call was initiated (promoted very early)\n\n🟢 Twitter \n\nDextools | Dexscreener | Pump",
    "links": [
      "https://t.me/auto007degen/42461",
      "https://www.dextools.io/app/en/solana/pair-explorer/8Bf9y8ZjWA1CUhbrFtE74TpsGuwWnC7aMp6AY3ppump",
      "https://instagram.com/phantom/p/DJpILVKKS6H",
      "https://dexscreener.com/solana/8Bf9y8ZjWA1CUhbrFtE74TpsGuwWnC7aMp6AY3ppump",
      "https://solscan.io/token/8Bf9y8ZjWA1CUhbrFtE74TpsGuwWnC7aMp6AY3ppump"
    ]
  }
]